milvus_correctness-0.1.0.dist-info/METADATA
milvus_correctness-0.1.0.dist-info/WHEEL
milvus_correctness-0.1.0.dist-info/entry_points.txt
milvus_correctness/__init__.py
milvus_correctness/calculators/state_calculator.py
milvus_correctness/core/framework.py
milvus_correctness/core/logging.py
milvus_correctness/core/milvus_client.py
milvus_correctness/core/models.py
milvus_correctness/generators/markov_generator.py
milvus_correctness/processors/request_processor.py
milvus_correctness/storage/base.py
milvus_correctness/storage/factory.py
milvus_correctness/storage/persist_queue_storage.py
milvus_correctness-0.1.0.dist-info/RECORD
