Metadata-Version: 2.1
Name: milvus-correctness
Version: 0.1.0
Summary: A framework for testing Milvus data correctness at scale
Author-Email: zhuwenxing <wenxing.zhu@zilliz.com>
License: MIT
Requires-Python: >=3.10
Requires-Dist: pymilvus>=2.3.6
Requires-Dist: persist-queue>=0.8.1
Requires-Dist: numpy>=1.26.4
Requires-Dist: pydantic>=2.6.4
Requires-Dist: loguru>=0.7.2
Requires-Dist: rich>=13.7.1
Requires-Dist: tqdm>=4.66.2
Requires-Dist: rocksdict>=0.3.25
